monday_code/__init__.py
monday_code/api_client.py
monday_code/api_response.py
monday_code/configuration.py
monday_code/exceptions.py
monday_code/py.typed
monday_code/rest.py
monday_code/api/__init__.py
monday_code/api/environment_variables_api.py
monday_code/api/logs_api.py
monday_code/api/queue_api.py
monday_code/api/secrets_api.py
monday_code/api/secure_storage_api.py
monday_code/api/storage_api.py
monday_code/models/__init__.py
monday_code/models/get_by_key_from_storage404_response.py
monday_code/models/get_by_key_from_storage500_response.py
monday_code/models/increment_counter200_response.py
monday_code/models/increment_counter200_response_any_of.py
monday_code/models/increment_counter200_response_any_of1.py
monday_code/models/increment_counter_params.py
monday_code/models/json_data_contract.py
monday_code/models/log_methods.py
monday_code/models/period.py
monday_code/models/publish_message_params.py
monday_code/models/publish_message_response.py
monday_code/models/storage_data_contract.py
monday_code/models/upsert_by_key_from_storage200_response.py
monday_code/models/upsert_by_key_from_storage200_response_any_of.py
monday_code/models/upsert_by_key_from_storage200_response_any_of1.py
monday_code/models/validate_secret_params.py
monday_code/models/validate_secret_response.py
monday_code/models/write_log_request_body.py
monday_code/models/write_log_request_body_error.py
monday_code-2.0.0.dist-info/METADATA
monday_code-2.0.0.dist-info/WHEEL
monday_code-2.0.0.dist-info/top_level.txt
monday_code-2.0.0.dist-info/RECORD
