Metadata-Version: 2.4
Name: monday-code
Version: 2.0.0
Summary: mcode-sdk-api
Home-page: 
Author: Monday.Com
Author-email: support@monday.com
License: MIT
Keywords: monday-code
Requires-Dist: urllib3<3.0.0,>=1.25.3
Requires-Dist: python-dateutil>=2.8.2
Requires-Dist: aiohttp>=3.8.4
Requires-Dist: aiohttp-retry>=2.8.3
Requires-Dist: pydantic>=2
Requires-Dist: typing-extensions>=4.7.1
Dynamic: author
Dynamic: author-email
Dynamic: description
Dynamic: description-content-type
Dynamic: keywords
Dynamic: license
Dynamic: requires-dist
Dynamic: summary
